setup.cfg
setup.py
dotteddict/__init__.py
dotteddict.egg-info/PKG-INFO
dotteddict.egg-info/SOURCES.txt
dotteddict.egg-info/dependency_links.txt
dotteddict.egg-info/top_level.txt