Metadata-Version: 1.0
Name: dotteddict
Version: 2016.3.11
Summary: Dictionary that allows nested dotting
Home-page: http://github.com/lnsybrd/dotteddict
Author: lnsy.brd
Author-email: lnsy.brd@gmail.com
License: UNKNOWN
Platform: UNKNOWN
